controller.v
// file: controller.v
// author: @amrgouhar

`timescale 1ns/1ns

module controller(go, clk, rst, cmp, sample, value, result, valid);
    parameter NOB = 8;
    
    input go;
    input clk;
    input rst;
    input [1:0]cmp;
    output reg sample;
    output reg valid;
    output reg [NOB-1:0]value;
    output reg [NOB-1:0] result;
    
    reg [NOB-1:0] first;
    reg [NOB-1:0] last;
    
    wire [NOB-1:0] mid = first + ((last-first) >> 1);
    
    always @(posedge clk or negedge rst) begin
        if(!rst) begin
            value <= {NOB{1'b0}};
            result <= {NOB{1'b0}};
            first <= {NOB{1'b0}};
            last <= {NOB{1'b1}};
            valid <= 1'b0;
            sample <= 1'b0;
        end
        else begin
            if(go) begin
                value <= mid;
                result <= {NOB{1'b0}};
                first <= {NOB{1'b0}};
                last <= {NOB{1'b1}};
                valid <= 1'b0;
                sample <= 1'b1;
            end
            else begin
            
                case(cmp)
                    2'b00:              //mid > result
                        begin
                            valid <= 1'b0;
                            last <= value;
                            value <= mid;
                        end
                    2'b01:
                        begin
                            valid <= 1'b0;
                            first <= value;
                            value <= mid;
                        end
                    default:
                        begin
                            valid <=1'b1;
                            result <= value;
                        end
                endcase
            end
        end
    end
    
endmodule

controller_tb.v
// file: controller_tb.v
// author: @amrgouhar
// Testbench for controller

`timescale 1ns/1ns

module controller_tb;

	//Inputs
	reg go;
	reg clk;
	reg rst;
	reg [1: 0] cmp;
    reg [7:0] vin;

	//Outputs
	wire sample;
	wire valid;
	wire [7: 0] value;
	wire [7: 0] result;


	//Instantiation of Unit Under Test
	controller uut (
		.go(go),
		.clk(clk),
		.rst(rst),
		.cmp(cmp),
		.sample(sample),
		.valid(valid),
		.value(value),
		.result(result)
	);

    always #2 clk = ~clk;

	initial begin
	//Inputs initialization
		go = 1;
		clk = 0;
		rst = 0;
		cmp = 0;
		vin = 64;
        #5 rst = 1;
        #10 go = 0;
	//Wait for the reset
		#1000;
    end
    
    always @(value) begin
        if (value > vin)
            cmp = 2'b00;
        else if (value < vin)
                cmp = 2'b01;
                else cmp = 2'b10;
    end
    
    always @(valid) begin
        if (valid) begin
            #5;
            $display("Vin under test is %0d, Program ouput is %0d ", vin, result);
            if (result != vin) begin
                $display("Failure");
            end
            else $display("Success");
            go = !go;
            vin = $random % 2**7 - 1;
            #10;
            go = !go;
        end
    end
    
endmodule

build (read-only)/controller_tb.vcd
$date
	Mon Feb 26 19:17:07 2018
$end
$version
	Icarus Verilog
$end
$timescale
	1ns
$end
$scope module controller_tb $end
$var wire 8 ! value [7:0] $end
$var wire 1 " valid $end
$var wire 1 # sample $end
$var wire 8 $ result [7:0] $end
$var reg 1 % clk $end
$var reg 2 & cmp [1:0] $end
$var reg 1 ' go $end
$var reg 1 ( rst $end
$var reg 8 ) vin [7:0] $end
$scope module uut $end
$var wire 1 % clk $end
$var wire 2 * cmp [1:0] $end
$var wire 1 ' go $end
$var wire 1 ( rst $end
$var wire 8 + mid [7:0] $end
$var reg 8 , first [7:0] $end
$var reg 8 - last [7:0] $end
$var reg 8 . result [7:0] $end
$var reg 1 # sample $end
$var reg 1 " valid $end
$var reg 8 / value [7:0] $end
$upscope $end
$upscope $end
$enddefinitions $end
#0
$dumpvars
b0 /
b0 .
b11111111 -
b0 ,
b1111111 +
b1 *
b1000000 )
0(
1'
b1 &
0%
b0 $
0#
0"
b0 !
$end
#2
1%
#4
0%
#5
1(
#6
b0 &
b0 *
1#
b1111111 !
b1111111 /
1%
#8
0%
#10
1%
#12
0%
#14
1%
#15
0'
#16
0%
#18
b111111 +
b1111111 -
1%
#20
0%
#22
b1 &
b1 *
b111111 !
b111111 /
1%
#24
0%
#26
b1011111 +
b111111 ,
1%
#28
0%
#30
b0 &
b0 *
b1011111 !
b1011111 /
1%
#32
0%
#34
b1001111 +
b1011111 -
1%
#36
0%
#38
b1001111 !
b1001111 /
1%
#40
0%
#42
b1000111 +
b1001111 -
1%
#44
0%
#46
b1000111 !
b1000111 /
1%
#48
0%
#50
b1000011 +
b1000111 -
1%
#52
0%
#54
b1000011 !
b1000011 /
1%
#56
0%
#58
b1000001 +
b1000011 -
1%
#60
0%
#62
b1000001 !
b1000001 /
1%
#64
0%
#66
b1000000 +
b1000001 -
1%
#68
0%
#70
b10 &
b10 *
b1000000 !
b1000000 /
1%
#72
0%
#74
b1000000 $
b1000000 .
1"
1%
#76
0%
#78
1%
#79
b100011 )
1'
#80
0%
#82
0"
b11111111 -
b1111111 +
b0 ,
b0 $
b0 .
1%
#84
0%
#86
b0 &
b0 *
b1111111 !
b1111111 /
1%
#88
0%
#89
0'
#90
b111111 +
b1111111 -
1%
#92
0%
#94
b111111 !
b111111 /
1%
#96
0%
#98
b11111 +
b111111 -
1%
#100
0%
#102
b1 &
b1 *
b11111 !
b11111 /
1%
#104
0%
#106
b101111 +
b11111 ,
1%
#108
0%
#110
b0 &
b0 *
b101111 !
b101111 /
1%
#112
0%
#114
b100111 +
b101111 -
1%
#116
0%
#118
b100111 !
b100111 /
1%
#120
0%
#122
b100011 +
b100111 -
1%
#124
0%
#126
b10 &
b10 *
b100011 !
b100011 /
1%
#128
0%
#130
b100011 $
b100011 .
1"
1%
#132
0%
#134
1%
#135
b10000000 )
1'
#136
0%
#138
0"
b11111111 -
b1111111 +
b0 ,
b0 $
b0 .
1%
#140
0%
#142
b1 &
b1 *
b1111111 !
b1111111 /
1%
#144
0%
#145
0'
#146
b10111111 +
b1111111 ,
1%
#148
0%
#150
b0 &
b0 *
b10111111 !
b10111111 /
1%
#152
0%
#154
b10011111 +
b10111111 -
1%
#156
0%
#158
b10011111 !
b10011111 /
1%
#160
0%
#162
b10001111 +
b10011111 -
1%
#164
0%
#166
b10001111 !
b10001111 /
1%
#168
0%
#170
b10000111 +
b10001111 -
1%
#172
0%
#174
b10000111 !
b10000111 /
1%
#176
0%
#178
b10000011 +
b10000111 -
1%
#180
0%
#182
b10000011 !
b10000011 /
1%
#184
0%
#186
b10000001 +
b10000011 -
1%
#188
0%
#190
b10000001 !
b10000001 /
1%
#192
0%
#194
b10000000 +
b10000001 -
1%
#196
0%
#198
b10 &
b10 *
b10000000 !
b10000000 /
1%
#200
0%
#202
b10000000 $
b10000000 .
1"
1%
#204
0%
#206
1%
#207
b10001000 )
1'
#208
0%
#210
0"
b11111111 -
b1111111 +
b0 ,
b0 $
b0 .
1%
#212
0%
#214
b1 &
b1 *
b1111111 !
b1111111 /
1%
#216
0%
#217
0'
#218
b10111111 +
b1111111 ,
1%
#220
0%
#222
b0 &
b0 *
b10111111 !
b10111111 /
1%
#224
0%
#226
b10011111 +
b10111111 -
1%
#228
0%
#230
b10011111 !
b10011111 /
1%
#232
0%
#234
b10001111 +
b10011111 -
1%
#236
0%
#238
b10001111 !
b10001111 /
1%
#240
0%
#242
b10000111 +
b10001111 -
1%
#244
0%
#246
b1 &
b1 *
b10000111 !
b10000111 /
1%
#248
0%
#250
b10001011 +
b10000111 ,
1%
#252
0%
#254
b0 &
b0 *
b10001011 !
b10001011 /
1%
#256
0%
#258
b10001001 +
b10001011 -
1%
#260
0%
#262
b10001001 !
b10001001 /
1%
#264
0%
#266
b10001000 +
b10001001 -
1%
#268
0%
#270
b10 &
b10 *
b10001000 !
b10001000 /
1%
#272
0%
#274
b10001000 $
b10001000 .
1"
1%
#276
0%
#278
1%
#279
b11100010 )
1'
#280
0%
#282
0"
b11111111 -
b1111111 +
b0 ,
b0 $
b0 .
1%
#284
0%
#286
b1 &
b1 *
b1111111 !
b1111111 /
1%
#288
0%
#289
0'
#290
b10111111 +
b1111111 ,
1%
#292
0%
#294
b10111111 !
b10111111 /
1%
#296
0%
#298
b11011111 +
b10111111 ,
1%
#300
0%
#302
b11011111 !
b11011111 /
1%
#304
0%
#306
b11101111 +
b11011111 ,
1%
#308
0%
#310
b0 &
b0 *
b11101111 !
b11101111 /
1%
#312
0%
#314
b11100111 +
b11101111 -
1%
#316
0%
#318
b11100111 !
b11100111 /
1%
#320
0%
#322
b11100011 +
b11100111 -
1%
#324
0%
#326
b11100011 !
b11100011 /
1%
#328
0%
#330
b11100001 +
b11100011 -
1%
#332
0%
#334
b1 &
b1 *
b11100001 !
b11100001 /
1%
#336
0%
#338
b11100010 +
b11100001 ,
1%
#340
0%
#342
b10 &
b10 *
b11100010 !
b11100010 /
1%
#344
0%
#346
b11100010 $
b11100010 .
1"
1%
#348
0%
#350
1%
#351
b1100 )
1'
#352
0%
#354
0"
b11111111 -
b1111111 +
b0 ,
b0 $
b0 .
1%
#356
0%
#358
b0 &
b0 *
b1111111 !
b1111111 /
1%
#360
0%
#361
0'
#362
b111111 +
b1111111 -
1%
#364
0%
#366
b111111 !
b111111 /
1%
#368
0%
#370
b11111 +
b111111 -
1%
#372
0%
#374
b11111 !
b11111 /
1%
#376
0%
#378
b1111 +
b11111 -
1%
#380
0%
#382
b1111 !
b1111 /
1%
#384
0%
#386
b111 +
b1111 -
1%
#388
0%
#390
b1 &
b1 *
b111 !
b111 /
1%
#392
0%
#394
b1011 +
b111 ,
1%
#396
0%
#398
b1011 !
b1011 /
1%
#400
0%
#402
b1101 +
b1011 ,
1%
#404
0%
#406
b0 &
b0 *
b1101 !
b1101 /
1%
#408
0%
#410
b1100 +
b1101 -
1%
#412
0%
#414
b10 &
b10 *
b1100 !
b1100 /
1%
#416
0%
#418
b1100 $
b1100 .
1"
1%
#420
0%
#422
1%
#423
1'
#424
0%
#426
0"
b11111111 -
b1111111 +
b0 ,
b0 $
b0 .
1%
#428
0%
#430
b0 &
b0 *
b1111111 !
b1111111 /
1%
#432
0%
#433
0'
#434
b111111 +
b1111111 -
1%
#436
0%
#438
b111111 !
b111111 /
1%
#440
0%
#442
b11111 +
b111111 -
1%
#444
0%
#446
b11111 !
b11111 /
1%
#448
0%
#450
b1111 +
b11111 -
1%
#452
0%
#454
b1111 !
b1111 /
1%
#456
0%
#458
b111 +
b1111 -
1%
#460
0%
#462
b1 &
b1 *
b111 !
b111 /
1%
#464
0%
#466
b1011 +
b111 ,
1%
#468
0%
#470
b1011 !
b1011 /
1%
#472
0%
#474
b1101 +
b1011 ,
1%
#476
0%
#478
b0 &
b0 *
b1101 !
b1101 /
1%
#480
0%
#482
b1100 +
b1101 -
1%
#484
0%
#486
b10 &
b10 *
b1100 !
b1100 /
1%
#488
0%
#490
b1100 $
b1100 .
1"
1%
#492
0%
#494
1%
#495
b11100100 )
1'
#496
0%
#498
0"
b11111111 -
b1111111 +
b0 ,
b0 $
b0 .
1%
#500
0%
#502
b1 &
b1 *
b1111111 !
b1111111 /
1%
#504
0%
#505
0'
#506
b10111111 +
b1111111 ,
1%
#508
0%
#510
b10111111 !
b10111111 /
1%
#512
0%
#514
b11011111 +
b10111111 ,
1%
#516
0%
#518
b11011111 !
b11011111 /
1%
#520
0%
#522
b11101111 +
b11011111 ,
1%
#524
0%
#526
b0 &
b0 *
b11101111 !
b11101111 /
1%
#528
0%
#530
b11100111 +
b11101111 -
1%
#532
0%
#534
b11100111 !
b11100111 /
1%
#536
0%
#538
b11100011 +
b11100111 -
1%
#540
0%
#542
b1 &
b1 *
b11100011 !
b11100011 /
1%
#544
0%
#546
b11100101 +
b11100011 ,
1%
#548
0%
#550
b0 &
b0 *
b11100101 !
b11100101 /
1%
#552
0%
#554
b11100100 +
b11100101 -
1%
#556
0%
#558
b10 &
b10 *
b11100100 !
b11100100 /
1%
#560
0%
#562
b11100100 $
b11100100 .
1"
1%
#564
0%
#566
1%
#567
b10010001 )
1'
#568
0%
#570
0"
b11111111 -
b1111111 +
b0 ,
b0 $
b0 .
1%
#572
0%
#574
b1 &
b1 *
b1111111 !
b1111111 /
1%
#576
0%
#577
0'
#578
b10111111 +
b1111111 ,
1%
#580
0%
#582
b0 &
b0 *
b10111111 !
b10111111 /
1%
#584
0%
#586
b10011111 +
b10111111 -
1%
#588
0%
#590
b10011111 !
b10011111 /
1%
#592
0%
#594
b10001111 +
b10011111 -
1%
#596
0%
#598
b1 &
b1 *
b10001111 !
b10001111 /
1%
#600
0%
#602
b10010111 +
b10001111 ,
1%
#604
0%
#606
b0 &
b0 *
b10010111 !
b10010111 /
1%
#608
0%
#610
b10010011 +
b10010111 -
1%
#612
0%
#614
b10010011 !
b10010011 /
1%
#616
0%
#618
b10010001 +
b10010011 -
1%
#620
0%
#622
b10 &
b10 *
b10010001 !
b10010001 /
1%
#624
0%
#626
b10010001 $
b10010001 .
1"
1%
#628
0%
#630
1%
#631
b0 )
1'
#632
0%
#634
0"
b11111111 -
b1111111 +
b0 ,
b0 $
b0 .
1%
#636
0%
#638
b0 &
b0 *
b1111111 !
b1111111 /
1%
#640
0%
#641
0'
#642
b111111 +
b1111111 -
1%
#644
0%
#646
b111111 !
b111111 /
1%
#648
0%
#650
b11111 +
b111111 -
1%
#652
0%
#654
b11111 !
b11111 /
1%
#656
0%
#658
b1111 +
b11111 -
1%
#660
0%
#662
b1111 !
b1111 /
1%
#664
0%
#666
b111 +
b1111 -
1%
#668
0%
#670
b111 !
b111 /
1%
#672
0%
#674
b11 +
b111 -
1%
#676
0%
#678
b11 !
b11 /
1%
#680
0%
#682
b1 +
b11 -
1%
#684
0%
#686
b1 !
b1 /
1%
#688
0%
#690
b0 +
b1 -
1%
#692
0%
#694
b10 &
b10 *
b0 !
b0 /
1%
#696
0%
#698
1"
1%
#700
0%
#702
1%
#703
b1100 )
1'
#704
0%
#706
b1111111 +
0"
b11111111 -
1%
#708
0%
#710
b0 &
b0 *
b1111111 !
b1111111 /
1%
#712
0%
#713
0'
#714
b111111 +
b1111111 -
1%
#716
0%
#718
b111111 !
b111111 /
1%
#720
0%
#722
b11111 +
b111111 -
1%
#724
0%
#726
b11111 !
b11111 /
1%
#728
0%
#730
b1111 +
b11111 -
1%
#732
0%
#734
b1111 !
b1111 /
1%
#736
0%
#738
b111 +
b1111 -
1%
#740
0%
#742
b1 &
b1 *
b111 !
b111 /
1%
#744
0%
#746
b1011 +
b111 ,
1%
#748
0%
#750
b1011 !
b1011 /
1%
#752
0%
#754
b1101 +
b1011 ,
1%
#756
0%
#758
b0 &
b0 *
b1101 !
b1101 /
1%
#760
0%
#762
b1100 +
b1101 -
1%
#764
0%
#766
b10 &
b10 *
b1100 !
b1100 /
1%
#768
0%
#770
b1100 $
b1100 .
1"
1%
#772
0%
#774
1%
#775
b1110101 )
1'
#776
0%
#778
0"
b11111111 -
b1111111 +
b0 ,
b0 $
b0 .
1%
#780
0%
#782
b0 &
b0 *
b1111111 !
b1111111 /
1%
#784
0%
#785
0'
#786
b111111 +
b1111111 -
1%
#788
0%
#790
b1 &
b1 *
b111111 !
b111111 /
1%
#792
0%
#794
b1011111 +
b111111 ,
1%
#796
0%
#798
b1011111 !
b1011111 /
1%
#800
0%
#802
b1101111 +
b1011111 ,
1%
#804
0%
#806
b1101111 !
b1101111 /
1%
#808
0%
#810
b1110111 +
b1101111 ,
1%
#812
0%
#814
b0 &
b0 *
b1110111 !
b1110111 /
1%
#816
0%
#818
b1110011 +
b1110111 -
1%
#820
0%
#822
b1 &
b1 *
b1110011 !
b1110011 /
1%
#824
0%
#826
b1110101 +
b1110011 ,
1%
#828
0%
#830
b10 &
b10 *
b1110101 !
b1110101 /
1%
#832
0%
#834
b1110101 $
b1110101 .
1"
1%
#836
0%
#838
1%
#839
b111100 )
1'
#840
0%
#842
0"
b11111111 -
b1111111 +
b0 ,
b0 $
b0 .
1%
#844
0%
#846
b0 &
b0 *
b1111111 !
b1111111 /
1%
#848
0%
#849
0'
#850
b111111 +
b1111111 -
1%
#852
0%
#854
b111111 !
b111111 /
1%
#856
0%
#858
b11111 +
b111111 -
1%
#860
0%
#862
b1 &
b1 *
b11111 !
b11111 /
1%
#864
0%
#866
b101111 +
b11111 ,
1%
#868
0%
#870
b101111 !
b101111 /
1%
#872
0%
#874
b110111 +
b101111 ,
1%
#876
0%
#878
b110111 !
b110111 /
1%
#880
0%
#882
b111011 +
b110111 ,
1%
#884
0%
#886
b111011 !
b111011 /
1%
#888
0%
#890
b111101 +
b111011 ,
1%
#892
0%
#894
b0 &
b0 *
b111101 !
b111101 /
1%
#896
0%
#898
b111100 +
b111101 -
1%
#900
0%
#902
b10 &
b10 *
b111100 !
b111100 /
1%
#904
0%
#906
b111100 $
b111100 .
1"
1%
#908
0%
#910
1%
#911
b1101100 )
1'
#912
0%
#914
0"
b11111111 -
b1111111 +
b0 ,
b0 $
b0 .
1%
#916
0%
#918
b0 &
b0 *
b1111111 !
b1111111 /
1%
#920
0%
#921
0'
#922
b111111 +
b1111111 -
1%
#924
0%
#926
b1 &
b1 *
b111111 !
b111111 /
1%
#928
0%
#930
b1011111 +
b111111 ,
1%
#932
0%
#934
b1011111 !
b1011111 /
1%
#936
0%
#938
b1101111 +
b1011111 ,
1%
#940
0%
#942
b0 &
b0 *
b1101111 !
b1101111 /
1%
#944
0%
#946
b1100111 +
b1101111 -
1%
#948
0%
#950
b1 &
b1 *
b1100111 !
b1100111 /
1%
#952
0%
#954
b1101011 +
b1100111 ,
1%
#956
0%
#958
b1101011 !
b1101011 /
1%
#960
0%
#962
b1101101 +
b1101011 ,
1%
#964
0%
#966
b0 &
b0 *
b1101101 !
b1101101 /
1%
#968
0%
#970
b1101100 +
b1101101 -
1%
#972
0%
#974
b10 &
b10 *
b1101100 !
b1101100 /
1%
#976
0%
#978
b1101100 $
b1101100 .
1"
1%
#980
0%
#982
1%
#983
b1011 )
1'
#984
0%
#986
0"
b11111111 -
b1111111 +
b0 ,
b0 $
b0 .
1%
#988
0%
#990
b0 &
b0 *
b1111111 !
b1111111 /
1%
#992
0%
#993
0'
#994
b111111 +
b1111111 -
1%
#996
0%
#998
b111111 !
b111111 /
1%
#1000
0%
#1002
b11111 +
b111111 -
1%
#1004
0%
#1006
b11111 !
b11111 /
1%
#1008
0%
#1010
b1111 +
b11111 -
1%
#1012
0%
#1014
b1111 !
b1111 /
1%
#1016
0%
#1018
b111 +
b1111 -
1%
#1020
0%
#1022
b1 &
b1 *
b111 !
b111 /
1%
#1024
0%
#1026
b1011 +
b111 ,
1%
#1028
0%
#1030
b10 &
b10 *
b1011 !
b1011 /
1%
#1032
0%
#1034
b1011 $
b1011 .
1"
1%
#1036
0%
#1038
1%
#1039
b1111000 )
1'
#1040
0%
#1042
0"
b11111111 -
b1111111 +
b0 ,
b0 $
b0 .
1%
#1044
0%
#1046
b0 &
b0 *
b1111111 !
b1111111 /
1%
#1048
0%
#1049
0'
#1050
b111111 +
b1111111 -
1%
#1052
0%
#1054
b1 &
b1 *
b111111 !
b111111 /
1%
#1056
0%
#1058
b1011111 +
b111111 ,
1%
#1060
0%
#1062
b1011111 !
b1011111 /
1%
#1064
0%
#1066
b1101111 +
b1011111 ,
1%
#1068
0%
#1070
b1101111 !
b1101111 /
1%
#1072
0%
#1074
b1110111 +
b1101111 ,
1%
#1076
0%
#1078
b1110111 !
b1110111 /
1%
#1080
0%
#1082
b1111011 +
b1110111 ,
1%
#1084
0%
#1086
b0 &
b0 *
b1111011 !
b1111011 /
1%
#1088
0%
#1090
b1111001 +
b1111011 -
1%
#1092
0%
#1094
b1111001 !
b1111001 /
1%
#1096
0%
#1098
b1111000 +
b1111001 -
1%
#1100
0%
#1102
b10 &
b10 *
b1111000 !
b1111000 /
1%
#1104
0%
#1106
b1111000 $
b1111000 .
1"
1%
#1108
0%
#1110
1%
#1111
b11000101 )
1'
#1112
0%
#1114
0"
b11111111 -
b1111111 +
b0 ,
b0 $
b0 .
1%
#1116
0%
#1118
b1 &
b1 *
b1111111 !
b1111111 /
1%
#1120
0%
#1121
0'
#1122
b10111111 +
b1111111 ,
1%
#1124
0%
#1126
b10111111 !
b10111111 /
1%
#1128
0%
#1130
b11011111 +
b10111111 ,
1%
#1132
0%
#1134
b0 &
b0 *
b11011111 !
b11011111 /
1%
#1136
0%
#1138
b11001111 +
b11011111 -
1%
#1140
0%
#1142
b11001111 !
b11001111 /
1%
#1144
0%
#1146
b11000111 +
b11001111 -
1%
#1148
0%
#1150
b11000111 !
b11000111 /
1%
#1152
0%
#1154
b11000011 +
b11000111 -
1%
#1156
0%
#1158
b1 &
b1 *
b11000011 !
b11000011 /
1%
#1160
0%
#1162
b11000101 +
b11000011 ,
1%
#1164
0%
#1166
b10 &
b10 *
b11000101 !
b11000101 /
1%
#1168
0%
#1170
b11000101 $
b11000101 .
1"
1%
#1172
0%
#1174
1%
#1175
b11000100 )
1'
#1176
0%
#1178
0"
b11111111 -
b1111111 +
b0 ,
b0 $
b0 .
1%
#1180
0%
#1182
b1 &
b1 *
b1111111 !
b1111111 /
1%
#1184
0%
#1185
0'
#1186
b10111111 +
b1111111 ,
1%
#1188
0%
#1190
b10111111 !
b10111111 /
1%
#1192
0%
#1194
b11011111 +
b10111111 ,
1%
#1196
0%
#1198
b0 &
b0 *
b11011111 !
b11011111 /
1%
#1200
0%
#1202
b11001111 +
b11011111 -
1%
#1204
0%
#1206
b11001111 !
b11001111 /
1%
#1208
0%
#1210
b11000111 +
b11001111 -
1%
#1212
0%
#1214
b11000111 !
b11000111 /
1%
#1216
0%
#1218
b11000011 +
b11000111 -
1%
#1220
0%
#1222
b1 &
b1 *
b11000011 !
b11000011 /
1%
#1224
0%
#1226
b11000101 +
b11000011 ,
1%
#1228
0%
#1230
b0 &
b0 *
b11000101 !
b11000101 /
1%
#1232
0%
#1234
b11000100 +
b11000101 -
1%
#1236
0%
#1238
b10 &
b10 *
b11000100 !
b11000100 /
1%
#1240
0%
#1242
b11000100 $
b11000100 .
1"
1%
#1244
0%
#1246
1%
#1247
b10101001 )
1'
#1248
0%
#1250
0"
b11111111 -
b1111111 +
b0 ,
b0 $
b0 .
1%
#1252
0%
#1254
b1 &
b1 *
b1111111 !
b1111111 /
1%
#1256
0%
#1257
0'
#1258
b10111111 +
b1111111 ,
1%
#1260
0%
#1262
b0 &
b0 *
b10111111 !
b10111111 /
1%
#1264
0%
#1266
b10011111 +
b10111111 -
1%
#1268
0%
#1270
b1 &
b1 *
b10011111 !
b10011111 /
1%
#1272
0%
#1274
b10101111 +
b10011111 ,
1%
#1276
0%
#1278
b0 &
b0 *
b10101111 !
b10101111 /
1%
#1280
0%
#1282
b10100111 +
b10101111 -
1%
#1284
0%
#1286
b1 &
b1 *
b10100111 !
b10100111 /
1%
#1288
0%
#1290
b10101011 +
b10100111 ,
1%
#1292
0%
#1294
b0 &
b0 *
b10101011 !
b10101011 /
1%
#1296
0%
#1298
b10101001 +
b10101011 -
1%
#1300
0%
#1302
b10 &
b10 *
b10101001 !
b10101001 /
1%
#1304
0%
#1306
b10101001 $
b10101001 .
1"
1%
#1308
0%
#1310
1%
#1311
b1100100 )
1'
#1312
0%
#1314
0"
b11111111 -
b1111111 +
b0 ,
b0 $
b0 .
1%
#1316
0%
#1318
b0 &
b0 *
b1111111 !
b1111111 /
1%
#1320
0%
#1321
0'
#1322
b111111 +
b1111111 -
1%
#1324
0%
#1326
b1 &
b1 *
b111111 !
b111111 /
1%
#1328
0%
#1330
b1011111 +
b111111 ,
1%
#1332
0%
#1334
b1011111 !
b1011111 /
1%
#1336
0%
#1338
b1101111 +
b1011111 ,
1%
#1340
0%
#1342
b0 &
b0 *
b1101111 !
b1101111 /
1%
#1344
0%
#1346
b1100111 +
b1101111 -
1%
#1348
0%
#1350
b1100111 !
b1100111 /
1%
#1352
0%
#1354
b1100011 +
b1100111 -
1%
#1356
0%
#1358
b1 &
b1 *
b1100011 !
b1100011 /
1%
#1360
0%
#1362
b1100101 +
b1100011 ,
1%
#1364
0%
#1366
b0 &
b0 *
b1100101 !
b1100101 /
1%
#1368
0%
#1370
b1100100 +
b1100101 -
1%
#1372
0%
#1374
b10 &
b10 *
b1100100 !
b1100100 /
1%
#1376
0%
#1378
b1100100 $
b1100100 .
1"
1%
#1380
0%
#1382
1%
#1383
b11110110 )
1'
#1384
0%
#1386
0"
b11111111 -
b1111111 +
b0 ,
b0 $
b0 .
1%
#1388
0%
#1390
b1 &
b1 *
b1111111 !
b1111111 /
1%
#1392
0%
#1393
0'
#1394
b10111111 +
b1111111 ,
1%
#1396
0%
#1398
b10111111 !
b10111111 /
1%
#1400
0%
#1402
b11011111 +
b10111111 ,
1%
#1404
0%
#1406
b11011111 !
b11011111 /
1%
#1408
0%
#1410
b11101111 +
b11011111 ,
1%
#1412
0%
#1414
b11101111 !
b11101111 /
1%
#1416
0%
#1418
b11110111 +
b11101111 ,
1%
#1420
0%
#1422
b0 &
b0 *
b11110111 !
b11110111 /
1%
#1424
0%
#1426
b11110011 +
b11110111 -
1%
#1428
0%
#1430
b1 &
b1 *
b11110011 !
b11110011 /
1%
#1432
0%
#1434
b11110101 +
b11110011 ,
1%
#1436
0%
#1438
b11110101 !
b11110101 /
1%
#1440
0%
#1442
b11110110 +
b11110101 ,
1%
#1444
0%
#1446
b10 &
b10 *
b11110110 !
b11110110 /
1%
#1448
0%
#1450
b11110110 $
b11110110 .
1"
1%
#1452
0%
#1454
1%
#1455
b10010001 )
1'
#1456
0%
#1458
0"
b11111111 -
b1111111 +
b0 ,
b0 $
b0 .
1%
#1460
0%
#1462
b1 &
b1 *
b1111111 !
b1111111 /
1%
#1464
0%
#1465
0'
#1466
b10111111 +
b1111111 ,
1%
#1468
0%
#1470
b0 &
b0 *
b10111111 !
b10111111 /
1%
#1472
0%
#1474
b10011111 +
b10111111 -
1%
#1476
0%
#1478
b10011111 !
b10011111 /
1%
#1480
0%
#1482
b10001111 +
b10011111 -
1%
#1484
0%
#1486
b1 &
b1 *
b10001111 !
b10001111 /
1%
#1488
0%
#1490
b10010111 +
b10001111 ,
1%
#1492
0%
#1494
b0 &
b0 *
b10010111 !
b10010111 /
1%
#1496
0%
#1498
b10010011 +
b10010111 -
1%
#1500
0%
#1502
b10010011 !
b10010011 /
1%
#1504
0%
#1506
b10010001 +
b10010011 -
1%
#1508
0%
#1510
b10 &
b10 *
b10010001 !
b10010001 /
1%
#1512
0%
#1514
b10010001 $
b10010001 .
1"
1%
#1516
0%
#1518
1%
#1519
b1110 )
1'
#1520
0%
#1522
0"
b11111111 -
b1111111 +
b0 ,
b0 $
b0 .
1%
#1524
0%
#1526
b0 &
b0 *
b1111111 !
b1111111 /
1%
#1528
0%
#1529
0'
#1530
b111111 +
b1111111 -
1%
#1532
0%
#1534
b111111 !
b111111 /
1%
#1536
0%
#1538
b11111 +
b111111 -
1%
#1540
0%
#1542
b11111 !
b11111 /
1%
#1544
0%
#1546
b1111 +
b11111 -
1%
#1548
0%
#1550
b1111 !
b1111 /
1%
#1552
0%
#1554
b111 +
b1111 -
1%
#1556
0%
#1558
b1 &
b1 *
b111 !
b111 /
1%
#1560
0%
#1562
b1011 +
b111 ,
1%
#1564
0%
#1566
b1011 !
b1011 /
1%
#1568
0%
#1570
b1101 +
b1011 ,
1%
#1572
0%
#1574
b1101 !
b1101 /
1%
#1576
0%
#1578
b1110 +
b1101 ,
1%
#1580
0%
#1582
b10 &
b10 *
b1110 !
b1110 /
1%
#1584
0%
#1586
b1110 $
b1110 .
1"
1%
#1588
0%
#1590
1%
#1591
b1110001 )
1'
#1592
0%
#1594
0"
b11111111 -
b1111111 +
b0 ,
b0 $
b0 .
1%
#1596
0%
#1598
b0 &
b0 *
b1111111 !
b1111111 /
1%
#1600
0%
#1601
0'
#1602
b111111 +
b1111111 -
1%
#1604
0%
#1606
b1 &
b1 *
b111111 !
b111111 /
1%
#1608
0%
#1610
b1011111 +
b111111 ,
1%
#1612
0%
#1614
b1011111 !
b1011111 /
1%
#1616
0%
#1618
b1101111 +
b1011111 ,
1%
#1620
0%
#1622
b1101111 !
b1101111 /
1%
#1624
0%
#1626
b1110111 +
b1101111 ,
1%
#1628
0%
#1630
b0 &
b0 *
b1110111 !
b1110111 /
1%
#1632
0%
#1634
b1110011 +
b1110111 -
1%
#1636
0%
#1638
b1110011 !
b1110011 /
1%
#1640
0%
#1642
b1110001 +
b1110011 -
1%
#1644
0%
#1646
b10 &
b10 *
b1110001 !
b1110001 /
1%
#1648
0%
#1650
b1110001 $
b1110001 .
1"
1%
#1652
0%
#1654
1%
#1655
b11001101 )
1'
#1656
0%
#1658
0"
b11111111 -
b1111111 +
b0 ,
b0 $
b0 .
1%
#1660
0%
#1662
b1 &
b1 *
b1111111 !
b1111111 /
1%
#1664
0%
#1665
0'
#1666
b10111111 +
b1111111 ,
1%
#1668
0%
#1670
b10111111 !
b10111111 /
1%
#1672
0%
#1674
b11011111 +
b10111111 ,
1%
#1676
0%
#1678
b0 &
b0 *
b11011111 !
b11011111 /
1%
#1680
0%
#1682
b11001111 +
b11011111 -
1%
#1684
0%
#1686
b11001111 !
b11001111 /
1%
#1688
0%
#1690
b11000111 +
b11001111 -
1%
#1692
0%
#1694
b1 &
b1 *
b11000111 !
b11000111 /
1%
#1696
0%
#1698
b11001011 +
b11000111 ,
1%
#1700
0%
#1702
b11001011 !
b11001011 /
1%
#1704
0%
#1706
b11001101 +
b11001011 ,
1%
#1708
0%
#1710
b10 &
b10 *
b11001101 !
b11001101 /
1%
#1712
0%
#1714
b11001101 $
b11001101 .
1"
1%
#1716
0%
#1718
1%
#1719
b11100111 )
1'
#1720
0%
#1722
0"
b11111111 -
b1111111 +
b0 ,
b0 $
b0 .
1%
#1724
0%
#1726
b1 &
b1 *
b1111111 !
b1111111 /
1%
#1728
0%
#1729
0'
#1730
b10111111 +
b1111111 ,
1%
#1732
0%
#1734
b10111111 !
b10111111 /
1%
#1736
0%
#1738
b11011111 +
b10111111 ,
1%
#1740
0%
#1742
b11011111 !
b11011111 /
1%
#1744
0%
#1746
b11101111 +
b11011111 ,
1%
#1748
0%
#1750
b0 &
b0 *
b11101111 !
b11101111 /
1%
#1752
0%
#1754
b11100111 +
b11101111 -
1%
